__init__.py
app.py
agents/__init__.py
agents/company_research_agent.py
agents/competitive_landscape_agent.py
agents/industry_analysis_agent.py
agents/market_data_agent.py
agents/market_gap_agent.py
agents/opportunity_agent.py
agents/report_synthesis_agent.py
api/__init__.py
api/router.py
api/routes/__init__.py
api/routes/company_research_routes.py
api/routes/competitive_landscape_routes.py
api/routes/industry_analysis_routes.py
api/routes/market_data_routes.py
api/routes/market_gap_routes.py
api/routes/opportunity_routes.py
api/routes/report_synthesis_routes.py
cli/__init__.py
cli/main.py
cli/commands/__init__.py
cli/commands/api_server.py
cli/commands/both.py
cli/commands/mcp_server.py
cli/commands/pipeline.py
cli/commands/run.py
cli/commands/tui.py
cli/tui/__init__.py
cli/tui/agent_info.py
cli/tui/app.py
cli/tui/environment_setup.py
cli/tui/individual_agent_runner.py
cli/tui/menus.py
cli/tui/server_status.py
cli/tui/agent_runner/__init__.py
cli/tui/agent_runner/agent_executor.py
cli/tui/agent_runner/display_utils.py
cli/tui/agent_runner/main_runner.py
cli/tui/agent_runner/report_handler.py
cli/tui/agent_runner/system_status.py
mcp_server/__init__.py
mcp_server/server.py
mcp_server/data_sources/__init__.py
mcp_server/tools/__init__.py
mcp_server/tools/citation_agent_tool.py
mcp_server/tools/ping_tool.py
mcp_server/tools/search_tool.py
pipeline/__init__.py
pipeline/pipeline.py
utils/__init__.py
utils/mcp_manager.py
utils/models.py
utils/validation.py
ambitus_cli-0.1.0.dist-info/METADATA
ambitus_cli-0.1.0.dist-info/WHEEL
ambitus_cli-0.1.0.dist-info/entry_points.txt
ambitus_cli-0.1.0.dist-info/top_level.txt
ambitus_cli-0.1.0.dist-info/RECORD
