Metadata-Version: 2.4
Name: ambitus-cli
Version: 0.1.0
Summary: a TUI‑first Python package and multi‑agent market research engine that orchestrates validated data collection, analysis, and report synthesis into citation‑rich PDF reports
Requires-Python: >=3.11
Requires-Dist: click>=8.1.8
Requires-Dist: docstring-parser>=0.16
Requires-Dist: duckduckgo-api-haystack>=0.1.15
Requires-Dist: fastapi[all]>=0.115.14
Requires-Dist: fastmcp>=2.5.0
Requires-Dist: haystack-ai>=2.13.2
Requires-Dist: jinja2>=3.1.6
Requires-Dist: jq>=1.8.0
Requires-Dist: markdown-it-py>=3.0.0
Requires-Dist: mcp-haystack>=0.2.0
Requires-Dist: mdit-plain>=1.0.1
Requires-Dist: openpyxl>=3.1.5
Requires-Dist: pandas>=2.2.3
Requires-Dist: pypdf>=5.5.0
Requires-Dist: python-docx>=1.1.2
Requires-Dist: python-pptx>=1.0.2
Requires-Dist: requests>=2.32.3
Requires-Dist: rich>=14.0.0
Requires-Dist: tabulate>=0.9.0
Requires-Dist: trafilatura>=2.0.0
Requires-Dist: uvicorn>=0.34.2
Requires-Dist: weasyprint>=65.1
